pylint_junit/__init__.py
pylint_junit/version.py
pylint_junit-0.3.5.dist-info/METADATA
pylint_junit-0.3.5.dist-info/WHEEL
pylint_junit-0.3.5.dist-info/top_level.txt
pylint_junit-0.3.5.dist-info/RECORD
